setup.py
pyace/__init__.py
pyace/aceeval.py
pyace/datagen.py
pyace/pyace.py
pyace/train.py
pyace.egg-info/PKG-INFO
pyace.egg-info/SOURCES.txt
pyace.egg-info/dependency_links.txt
pyace.egg-info/requires.txt
pyace.egg-info/top_level.txt
pyace/chordlyrics/__init__.py
pyace/chordlyrics/chordlyrics.py
pyace/fe/__init__.py
pyace/fe/fe.py
pyace/helpers/__init__.py
pyace/helpers/helpers.py
pyace/songtranspose/__init__.py
pyace/songtranspose/songtranspose.py