Metadata-Version: 1.1
Name: pyace
Version: 0.1.1
Summary: A minimal python implementation of automatic chord estimation
Home-page: https://github.com/tangkk/pyace
Author: Junqi Deng
Author-email: dengjunqi06323011@gmail.com
License: BSD
Keywords: audio music chord mir
Platform: UNKNOWN
Classifier: License :: OSI Approved :: BSD License
Classifier: Programming Language :: Python
Classifier: Programming Language :: Python :: 2.7
Classifier: Topic :: Multimedia :: Sound/Audio
